<?xml version="1.0" standalone="yes" ?>
<DBMODEL Version="4.0">
<SETTINGS>
<GLOBALSETTINGS ModelName="sihos" IDModel="0" IDVersion="0" VersionStr="1.0.0.0" Comments="" UseVersionHistroy="1" AutoIncVersion="1" DatabaseType="MySQL" ZoomFac="31.64" XPos="0" YPos="72" DefaultDataType="5" DefaultTablePrefix="0" DefSaveDBConn="" DefSyncDBConn="" DefQueryDBConn="" Printer="Samsung ML-2250 Series" HPageCount="3.564838990426458" PageAspectRatio="1.431813406177768" PageOrientation="0" PageFormat="A4 (210x297 mm, 8.26x11.7 inches)" SelectedPages="" UsePositionGrid="0" PositionGridX="20" PositionGridY="20" TableNameInRefs="0" DefaultTableType="1" ActivateRefDefForNewRelations="1" FKPrefix="" FKPostfix="" CreateFKRefDefIndex="0" DBQuoteCharacter="`" CreateSQLforLinkedObjects="0" DefModelFont="Tahoma" CanvasWidth="4096" CanvasHeight="2842" />
<DATATYPEGROUPS>
<DATATYPEGROUP Name="Numeric Types" Icon="1" />
<DATATYPEGROUP Name="Date and Time Types" Icon="2" />
<DATATYPEGROUP Name="String Types" Icon="3" />
<DATATYPEGROUP Name="Blob and Text Types" Icon="4" />
<DATATYPEGROUP Name="User defined Types" Icon="5" />
<DATATYPEGROUP Name="Geographic Types" Icon="6" />
</DATATYPEGROUPS>
<DATATYPES>
<DATATYPE ID="1" IDGroup="0" TypeName="TINYINT" Description="A very small integer. The signed range is -128 to 127. The unsigned range is 0 to 255." ParamCount="1" OptionCount="2" ParamRequired="0" EditParamsAsString="0" SynonymGroup="0" PhysicalMapping="0" PhysicalTypeName="" >
<PARAMS>
<PARAM Name="length" />
</PARAMS>
<OPTIONS>
<OPTION Name="UNSIGNED" Default="1" />
<OPTION Name="ZEROFILL" Default="0" />
</OPTIONS>
</DATATYPE>
<DATATYPE ID="2" IDGroup="0" TypeName="SMALLINT" Description="A small integer. The signed range is -32768 to 32767. The unsigned range is 0 to 65535." ParamCount="1" OptionCount="2" ParamRequired="0" EditParamsAsString="0" SynonymGroup="0" PhysicalMapping="0" PhysicalTypeName="" >
<PARAMS>
<PARAM Name="length" />
</PARAMS>
<OPTIONS>
<OPTION Name="UNSIGNED" Default="1" />
<OPTION Name="ZEROFILL" Default="0" />
</OPTIONS>
</DATATYPE>
<DATATYPE ID="3" IDGroup="0" TypeName="MEDIUMINT" Description="A medium-size integer. The signed range is -8388608 to 8388607. The unsigned range is 0 to 16777215." ParamCount="1" OptionCount="2" ParamRequired="0" EditParamsAsString="0" SynonymGroup="0" PhysicalMapping="0" PhysicalTypeName="" >
<PARAMS>
<PARAM Name="length" />
</PARAMS>
<OPTIONS>
<OPTION Name="UNSIGNED" Default="1" />
<OPTION Name="ZEROFILL" Default="0" />
</OPTIONS>
</DATATYPE>
<DATATYPE ID="4" IDGroup="0" TypeName="INT" Description="A normal-size integer. The signed range is -2147483648 to 2147483647. The unsigned range is 0 to 4294967295." ParamCount="1" OptionCount="2" ParamRequired="0" EditParamsAsString="0" SynonymGroup="1" PhysicalMapping="0" PhysicalTypeName="" >
<PARAMS>
<PARAM Name="length" />
</PARAMS>
<OPTIONS>
<OPTION Name="UNSIGNED" Default="0" />
<OPTION Name="ZEROFILL" Default="0" />
</OPTIONS>
</DATATYPE>
<DATATYPE ID="5" IDGroup="0" TypeName="INTEGER" Description="A normal-size integer. The signed range is -2147483648 to 2147483647. The unsigned range is 0 to 4294967295." ParamCount="1" OptionCount="2" ParamRequired="0" EditParamsAsString="0" SynonymGroup="1" PhysicalMapping="0" PhysicalTypeName="" >
<PARAMS>
<PARAM Name="length" />
</PARAMS>
<OPTIONS>
<OPTION Name="UNSIGNED" Default="1" />
<OPTION Name="ZEROFILL" Default="0" />
</OPTIONS>
</DATATYPE>
<DATATYPE ID="6" IDGroup="0" TypeName="BIGINT" Description="A large integer. The signed range is -9223372036854775808 to 9223372036854775807. The unsigned range is 0 to 18446744073709551615." ParamCount="1" OptionCount="2" ParamRequired="0" EditParamsAsString="0" SynonymGroup="0" PhysicalMapping="0" PhysicalTypeName="" >
<PARAMS>
<PARAM Name="length" />
</PARAMS>
<OPTIONS>
<OPTION Name="UNSIGNED" Default="0" />
<OPTION Name="ZEROFILL" Default="0" />
</OPTIONS>
</DATATYPE>
<DATATYPE ID="7" IDGroup="0" TypeName="FLOAT" Description="A small (single-precision) floating-point number. Cannot be unsigned. Allowable values are -3.402823466E+38 to -1.175494351E-38, 0, and 1.175494351E-38 to 3.402823466E+38." ParamCount="1" OptionCount="1" ParamRequired="1" EditParamsAsString="0" SynonymGroup="0" PhysicalMapping="0" PhysicalTypeName="" >
<PARAMS>
<PARAM Name="precision" />
</PARAMS>
<OPTIONS>
<OPTION Name="ZEROFILL" Default="0" />
</OPTIONS>
</DATATYPE>
<DATATYPE ID="8" IDGroup="0" TypeName="FLOAT" Description="A small (single-precision) floating-point number. Cannot be unsigned. Allowable values are -3.402823466E+38 to -1.175494351E-38, 0, and 1.175494351E-38 to 3.402823466E+38." ParamCount="2" OptionCount="1" ParamRequired="0" EditParamsAsString="0" SynonymGroup="0" PhysicalMapping="0" PhysicalTypeName="" >
<PARAMS>
<PARAM Name="length" />
<PARAM Name="decimals" />
</PARAMS>
<OPTIONS>
<OPTION Name="ZEROFILL" Default="0" />
</OPTIONS>
</DATATYPE>
<DATATYPE ID="9" IDGroup="0" TypeName="DOUBLE" Description="A normal-size (double-precision) floating-point number. Cannot be unsigned. Allowable values are -1.7976931348623157E+308 to -2.2250738585072014E-308, 0, and 2.2250738585072014E-308 to 1.7976931348623157E+308." ParamCount="2" OptionCount="1" ParamRequired="0" EditParamsAsString="0" SynonymGroup="2" PhysicalMapping="0" PhysicalTypeName="" >
<PARAMS>
<PARAM Name="length" />
<PARAM Name="decimals" />
</PARAMS>
<OPTIONS>
<OPTION Name="ZEROFILL" Default="0" />
</OPTIONS>
</DATATYPE>
<DATATYPE ID="10" IDGroup="0" TypeName="DOUBLE PRECISION" Description="This is a synonym for DOUBLE." ParamCount="2" OptionCount="1" ParamRequired="0" EditParamsAsString="0" SynonymGroup="2" PhysicalMapping="0" PhysicalTypeName="" >
<PARAMS>
<PARAM Name="length" />
<PARAM Name="decimals" />
</PARAMS>
<OPTIONS>
<OPTION Name="ZEROFILL" Default="0" />
</OPTIONS>
</DATATYPE>
<DATATYPE ID="11" IDGroup="0" TypeName="REAL" Description="This is a synonym for DOUBLE." ParamCount="2" OptionCount="1" ParamRequired="0" EditParamsAsString="0" SynonymGroup="2" PhysicalMapping="0" PhysicalTypeName="" >
<PARAMS>
<PARAM Name="length" />
<PARAM Name="decimals" />
</PARAMS>
<OPTIONS>
<OPTION Name="ZEROFILL" Default="0" />
</OPTIONS>
</DATATYPE>
<DATATYPE ID="12" IDGroup="0" TypeName="DECIMAL" Description="An unpacked floating-point number. Cannot be unsigned. Behaves like a CHAR column." ParamCount="2" OptionCount="1" ParamRequired="0" EditParamsAsString="0" SynonymGroup="3" PhysicalMapping="0" PhysicalTypeName="" >
<PARAMS>
<PARAM Name="length" />
<PARAM Name="decimals" />
</PARAMS>
<OPTIONS>
<OPTION Name="ZEROFILL" Default="0" />
</OPTIONS>
</DATATYPE>
<DATATYPE ID="13" IDGroup="0" TypeName="NUMERIC" Description="This is a synonym for DECIMAL." ParamCount="2" OptionCount="1" ParamRequired="1" EditParamsAsString="0" SynonymGroup="3" PhysicalMapping="0" PhysicalTypeName="" >
<PARAMS>
<PARAM Name="length" />
<PARAM Name="decimals" />
</PARAMS>
<OPTIONS>
<OPTION Name="ZEROFILL" Default="0" />
</OPTIONS>
</DATATYPE>
<DATATYPE ID="14" IDGroup="1" TypeName="DATE" Description="A date. The supported range is \a1000-01-01\a to \a9999-12-31\a." ParamCount="0" OptionCount="0" ParamRequired="0" EditParamsAsString="0" SynonymGroup="0" PhysicalMapping="0" PhysicalTypeName="" >
</DATATYPE>
<DATATYPE ID="15" IDGroup="1" TypeName="DATETIME" Description="A date and time combination. The supported range is \a1000-01-01 00:00:00\a to \a9999-12-31 23:59:59\a." ParamCount="0" OptionCount="0" ParamRequired="0" EditParamsAsString="0" SynonymGroup="0" PhysicalMapping="0" PhysicalTypeName="" >
</DATATYPE>
<DATATYPE ID="16" IDGroup="1" TypeName="TIMESTAMP" Description="A timestamp. The range is \a1970-01-01 00:00:00\a to sometime in the year 2037. The length can be 14 (or missing), 12, 10, 8, 6, 4, or 2 representing YYYYMMDDHHMMSS, ... , YYYYMMDD, ... , YY formats." ParamCount="1" OptionCount="0" ParamRequired="0" EditParamsAsString="0" SynonymGroup="0" PhysicalMapping="0" PhysicalTypeName="" >
<PARAMS>
<PARAM Name="length" />
</PARAMS>
</DATATYPE>
<DATATYPE ID="17" IDGroup="1" TypeName="TIME" Description="A time. The range is \a-838:59:59\a to \a838:59:59\a." ParamCount="0" OptionCount="0" ParamRequired="0" EditParamsAsString="0" SynonymGroup="0" PhysicalMapping="0" PhysicalTypeName="" >
</DATATYPE>
<DATATYPE ID="18" IDGroup="1" TypeName="YEAR" Description="A year in 2- or 4-digit format (default is 4-digit)." ParamCount="1" OptionCount="0" ParamRequired="0" EditParamsAsString="0" SynonymGroup="0" PhysicalMapping="0" PhysicalTypeName="" >
<PARAMS>
<PARAM Name="length" />
</PARAMS>
</DATATYPE>
<DATATYPE ID="19" IDGroup="2" TypeName="CHAR" Description="A fixed-length string (1 to 255 characters) that is always right-padded with spaces to the specified length when stored. values are sorted and compared in case-insensitive fashion according to the default character set unless the BINARY keyword is given." ParamCount="1" OptionCount="1" ParamRequired="1" EditParamsAsString="0" SynonymGroup="0" PhysicalMapping="0" PhysicalTypeName="" >
<PARAMS>
<PARAM Name="length" />
</PARAMS>
<OPTIONS>
<OPTION Name="BINARY" Default="0" />
</OPTIONS>
</DATATYPE>
<DATATYPE ID="20" IDGroup="2" TypeName="VARCHAR" Description="A variable-length string (1 to 255 characters). Values are sorted and compared in case-sensitive fashion unless the BINARY keyword is given." ParamCount="1" OptionCount="1" ParamRequired="1" EditParamsAsString="0" SynonymGroup="0" PhysicalMapping="0" PhysicalTypeName="" >
<PARAMS>
<PARAM Name="length" />
</PARAMS>
<OPTIONS>
<OPTION Name="BINARY" Default="0" />
</OPTIONS>
</DATATYPE>
<DATATYPE ID="21" IDGroup="2" TypeName="BIT" Description="This is a synonym for CHAR(1)." ParamCount="0" OptionCount="0" ParamRequired="0" EditParamsAsString="0" SynonymGroup="0" PhysicalMapping="0" PhysicalTypeName="" >
</DATATYPE>
<DATATYPE ID="22" IDGroup="2" TypeName="BOOL" Description="This is a synonym for CHAR(1)." ParamCount="0" OptionCount="0" ParamRequired="0" EditParamsAsString="0" SynonymGroup="0" PhysicalMapping="0" PhysicalTypeName="" >
</DATATYPE>
<DATATYPE ID="23" IDGroup="3" TypeName="TINYBLOB" Description="A column maximum length of 255 (2^8 - 1) characters. Values are sorted and compared in case-sensitive fashion." ParamCount="0" OptionCount="0" ParamRequired="0" EditParamsAsString="0" SynonymGroup="0" PhysicalMapping="0" PhysicalTypeName="" >
</DATATYPE>
<DATATYPE ID="24" IDGroup="3" TypeName="BLOB" Description="A column maximum length of 65535 (2^16 - 1) characters. Values are sorted and compared in case-sensitive fashion." ParamCount="0" OptionCount="0" ParamRequired="0" EditParamsAsString="0" SynonymGroup="0" PhysicalMapping="0" PhysicalTypeName="" >
</DATATYPE>
<DATATYPE ID="25" IDGroup="3" TypeName="MEDIUMBLOB" Description="A column maximum length of 16777215 (2^24 - 1) characters. Values are sorted and compared in case-sensitive fashion." ParamCount="0" OptionCount="0" ParamRequired="0" EditParamsAsString="0" SynonymGroup="0" PhysicalMapping="0" PhysicalTypeName="" >
</DATATYPE>
<DATATYPE ID="26" IDGroup="3" TypeName="LONGBLOB" Description="A column maximum length of 4294967295 (2^32 - 1) characters. Values are sorted and compared in case-sensitive fashion." ParamCount="0" OptionCount="0" ParamRequired="0" EditParamsAsString="0" SynonymGroup="0" PhysicalMapping="0" PhysicalTypeName="" >
</DATATYPE>
<DATATYPE ID="27" IDGroup="3" TypeName="TINYTEXT" Description="A column maximum length of 255 (2^8 - 1) characters." ParamCount="0" OptionCount="0" ParamRequired="0" EditParamsAsString="0" SynonymGroup="0" PhysicalMapping="0" PhysicalTypeName="" >
</DATATYPE>
<DATATYPE ID="28" IDGroup="3" TypeName="TEXT" Description="A column maximum length of 65535 (2^16 - 1) characters." ParamCount="0" OptionCount="0" ParamRequired="0" EditParamsAsString="0" SynonymGroup="0" PhysicalMapping="0" PhysicalTypeName="" >
</DATATYPE>
<DATATYPE ID="29" IDGroup="3" TypeName="MEDIUMTEXT" Description="A column maximum length of 16777215 (2^24 - 1) characters." ParamCount="0" OptionCount="0" ParamRequired="0" EditParamsAsString="0" SynonymGroup="0" PhysicalMapping="0" PhysicalTypeName="" >
</DATATYPE>
<DATATYPE ID="30" IDGroup="3" TypeName="LONGTEXT" Description="A column maximum length of 4294967295 (2^32 - 1) characters." ParamCount="0" OptionCount="0" ParamRequired="0" EditParamsAsString="0" SynonymGroup="0" PhysicalMapping="0" PhysicalTypeName="" >
</DATATYPE>
<DATATYPE ID="31" IDGroup="3" TypeName="ENUM" Description="An enumeration. A string object that can have only one value, chosen from the list of values." ParamCount="1" OptionCount="0" ParamRequired="1" EditParamsAsString="1" SynonymGroup="0" PhysicalMapping="0" PhysicalTypeName="" >
<PARAMS>
<PARAM Name="values" />
</PARAMS>
</DATATYPE>
<DATATYPE ID="32" IDGroup="3" TypeName="SET" Description="A set. A string object that can have zero or more values, each of which must be chosen from the list of values." ParamCount="1" OptionCount="0" ParamRequired="1" EditParamsAsString="1" SynonymGroup="0" PhysicalMapping="0" PhysicalTypeName="" >
<PARAMS>
<PARAM Name="values" />
</PARAMS>
</DATATYPE>
<DATATYPE ID="33" IDGroup="4" TypeName="Varchar(20)" Description="" ParamCount="0" OptionCount="1" ParamRequired="0" EditParamsAsString="0" SynonymGroup="0" PhysicalMapping="0" PhysicalTypeName="" >
<OPTIONS>
<OPTION Name="BINARY" Default="0" />
</OPTIONS>
</DATATYPE>
<DATATYPE ID="34" IDGroup="4" TypeName="Varchar(45)" Description="" ParamCount="0" OptionCount="1" ParamRequired="0" EditParamsAsString="0" SynonymGroup="0" PhysicalMapping="0" PhysicalTypeName="" >
<OPTIONS>
<OPTION Name="BINARY" Default="0" />
</OPTIONS>
</DATATYPE>
<DATATYPE ID="35" IDGroup="4" TypeName="Varchar(255)" Description="" ParamCount="0" OptionCount="1" ParamRequired="0" EditParamsAsString="0" SynonymGroup="0" PhysicalMapping="0" PhysicalTypeName="" >
<OPTIONS>
<OPTION Name="BINARY" Default="0" />
</OPTIONS>
</DATATYPE>
<DATATYPE ID="36" IDGroup="5" TypeName="GEOMETRY" Description="Geographic Datatype" ParamCount="0" OptionCount="0" ParamRequired="0" EditParamsAsString="0" SynonymGroup="0" PhysicalMapping="0" PhysicalTypeName="" >
</DATATYPE>
<DATATYPE ID="38" IDGroup="5" TypeName="LINESTRING" Description="Geographic Datatype" ParamCount="0" OptionCount="0" ParamRequired="0" EditParamsAsString="0" SynonymGroup="0" PhysicalMapping="0" PhysicalTypeName="" >
</DATATYPE>
<DATATYPE ID="39" IDGroup="5" TypeName="POLYGON" Description="Geographic Datatype" ParamCount="0" OptionCount="0" ParamRequired="0" EditParamsAsString="0" SynonymGroup="0" PhysicalMapping="0" PhysicalTypeName="" >
</DATATYPE>
<DATATYPE ID="40" IDGroup="5" TypeName="MULTIPOINT" Description="Geographic Datatype" ParamCount="0" OptionCount="0" ParamRequired="0" EditParamsAsString="0" SynonymGroup="0" PhysicalMapping="0" PhysicalTypeName="" >
</DATATYPE>
<DATATYPE ID="41" IDGroup="5" TypeName="MULTILINESTRING" Description="Geographic Datatype" ParamCount="0" OptionCount="0" ParamRequired="0" EditParamsAsString="0" SynonymGroup="0" PhysicalMapping="0" PhysicalTypeName="" >
</DATATYPE>
<DATATYPE ID="42" IDGroup="5" TypeName="MULTIPOLYGON" Description="Geographic Datatype" ParamCount="0" OptionCount="0" ParamRequired="0" EditParamsAsString="0" SynonymGroup="0" PhysicalMapping="0" PhysicalTypeName="" >
</DATATYPE>
<DATATYPE ID="43" IDGroup="5" TypeName="GEOMETRYCOLLECTION" Description="Geographic Datatype" ParamCount="0" OptionCount="0" ParamRequired="0" EditParamsAsString="0" SynonymGroup="0" PhysicalMapping="0" PhysicalTypeName="" >
</DATATYPE>
</DATATYPES>
<COMMON_DATATYPES>
<COMMON_DATATYPE ID="5" />
<COMMON_DATATYPE ID="8" />
<COMMON_DATATYPE ID="20" />
<COMMON_DATATYPE ID="15" />
<COMMON_DATATYPE ID="22" />
<COMMON_DATATYPE ID="28" />
<COMMON_DATATYPE ID="26" />
<COMMON_DATATYPE ID="33" />
<COMMON_DATATYPE ID="34" />
<COMMON_DATATYPE ID="35" />
</COMMON_DATATYPES>
<TABLEPREFIXES>
<TABLEPREFIX Name="Default (no prefix)" />
</TABLEPREFIXES>
<REGIONCOLORS>
<REGIONCOLOR Color="Red=#FFEEEC" />
<REGIONCOLOR Color="Yellow=#FEFDED" />
<REGIONCOLOR Color="Green=#EAFFE5" />
<REGIONCOLOR Color="Cyan=#ECFDFF" />
<REGIONCOLOR Color="Blue=#F0F1FE" />
<REGIONCOLOR Color="Magenta=#FFEBFA" />
</REGIONCOLORS>
<POSITIONMARKERS>
<POSITIONMARKER ZoomFac="-1.0" X="0" Y="0" />
<POSITIONMARKER ZoomFac="-1.0" X="0" Y="0" />
<POSITIONMARKER ZoomFac="-1.0" X="0" Y="0" />
<POSITIONMARKER ZoomFac="-1.0" X="0" Y="0" />
<POSITIONMARKER ZoomFac="-1.0" X="0" Y="0" />
<POSITIONMARKER ZoomFac="-1.0" X="0" Y="0" />
<POSITIONMARKER ZoomFac="-1.0" X="0" Y="0" />
<POSITIONMARKER ZoomFac="-1.0" X="0" Y="0" />
<POSITIONMARKER ZoomFac="-1.0" X="0" Y="0" />
<POSITIONMARKER ZoomFac="-1.0" X="0" Y="0" />
<POSITIONMARKER ZoomFac="-1.0" X="0" Y="0" />
</POSITIONMARKERS>
</SETTINGS>
<METADATA>
<REGIONS>
</REGIONS>
<TABLES>
<TABLE ID="12787" Tablename="ihegresos" PrevTableName="" XPos="80" YPos="40" TableType="1" TablePrefix="0" nmTable="0" Temporary="0" UseStandardInserts="0" StandardInserts="" TableOptions="" Comments="" Collapsed="0" IsLinkedObject="0" IDLinkedModel="-1" Obj_id_Linked="-1" OrderPos="2" >
<COLUMNS>
<COLUMN ID="12788" ColName="IHEGR_ZONA" PrevColName="" Pos="1" idDatatype="19" DatatypeParams="(1)" Width="0" Prec="0" PrimaryKey="1" NotNull="1" AutoInc="0" IsForeignKey="0" DefaultValue="" Comments="">
<OPTIONSELECTED>
<OPTIONSELECT Value="0" />
</OPTIONSELECTED>
</COLUMN>
<COLUMN ID="12789" ColName="IHEGR_CODDPTO" PrevColName="" Pos="2" idDatatype="19" DatatypeParams="(3)" Width="0" Prec="0" PrimaryKey="1" NotNull="1" AutoInc="0" IsForeignKey="0" DefaultValue="" Comments="">
<OPTIONSELECTED>
<OPTIONSELECT Value="0" />
</OPTIONSELECTED>
</COLUMN>
<COLUMN ID="12790" ColName="IHEGR_CODLOC" PrevColName="" Pos="3" idDatatype="19" DatatypeParams="(2)" Width="0" Prec="0" PrimaryKey="1" NotNull="1" AutoInc="0" IsForeignKey="0" DefaultValue="" Comments="">
<OPTIONSELECTED>
<OPTIONSELECT Value="0" />
</OPTIONSELECTED>
</COLUMN>
<COLUMN ID="12791" ColName="IHEGR_CODEST" PrevColName="" Pos="4" idDatatype="20" DatatypeParams="(5)" Width="0" Prec="0" PrimaryKey="1" NotNull="1" AutoInc="0" IsForeignKey="0" DefaultValue="" Comments="">
<OPTIONSELECTED>
<OPTIONSELECT Value="0" />
</OPTIONSELECTED>
</COLUMN>
<COLUMN ID="12792" ColName="IHEGR_DEPADM" PrevColName="" Pos="5" idDatatype="19" DatatypeParams="(1)" Width="0" Prec="0" PrimaryKey="1" NotNull="1" AutoInc="0" IsForeignKey="0" DefaultValue="" Comments="">
<OPTIONSELECTED>
<OPTIONSELECT Value="0" />
</OPTIONSELECTED>
</COLUMN>
<COLUMN ID="12793" ColName="IHEGR_ANOINFORME" PrevColName="" Pos="6" idDatatype="20" DatatypeParams="(4)" Width="0" Prec="0" PrimaryKey="1" NotNull="1" AutoInc="0" IsForeignKey="0" DefaultValue="" Comments="">
<OPTIONSELECTED>
<OPTIONSELECT Value="0" />
</OPTIONSELECTED>
</COLUMN>
<COLUMN ID="12794" ColName="IHEGR_NROINFORME" PrevColName="" Pos="7" idDatatype="20" DatatypeParams="(5)" Width="0" Prec="0" PrimaryKey="1" NotNull="1" AutoInc="0" IsForeignKey="0" DefaultValue="" Comments="">
<OPTIONSELECTED>
<OPTIONSELECT Value="0" />
</OPTIONSELECTED>
</COLUMN>
<COLUMN ID="12795" ColName="IHEGR_NROHISCLI" PrevColName="" Pos="8" idDatatype="20" DatatypeParams="(9)" Width="0" Prec="0" PrimaryKey="0" NotNull="1" AutoInc="0" IsForeignKey="0" DefaultValue="" Comments="">
<OPTIONSELECTED>
<OPTIONSELECT Value="0" />
</OPTIONSELECTED>
</COLUMN>
<COLUMN ID="12796" ColName="IHEGR_FECHANAC" PrevColName="" Pos="9" idDatatype="20" DatatypeParams="(10)" Width="0" Prec="0" PrimaryKey="0" NotNull="1" AutoInc="0" IsForeignKey="0" DefaultValue="" Comments="">
<OPTIONSELECTED>
<OPTIONSELECT Value="0" />
</OPTIONSELECTED>
</COLUMN>
<COLUMN ID="12797" ColName="IHEGR_TIPODOCUM" PrevColName="" Pos="10" idDatatype="19" DatatypeParams="(1)" Width="0" Prec="0" PrimaryKey="0" NotNull="1" AutoInc="0" IsForeignKey="0" DefaultValue="" Comments="">
<OPTIONSELECTED>
<OPTIONSELECT Value="0" />
</OPTIONSELECTED>
</COLUMN>
<COLUMN ID="12798" ColName="IHEGR_NRODOCUM" PrevColName="" Pos="11" idDatatype="20" DatatypeParams="(9)" Width="0" Prec="0" PrimaryKey="0" NotNull="1" AutoInc="0" IsForeignKey="0" DefaultValue="" Comments="">
<OPTIONSELECTED>
<OPTIONSELECT Value="0" />
</OPTIONSELECTED>
</COLUMN>
<COLUMN ID="12799" ColName="IHEGR_EDAD" PrevColName="" Pos="12" idDatatype="19" DatatypeParams="(3)" Width="0" Prec="0" PrimaryKey="0" NotNull="1" AutoInc="0" IsForeignKey="0" DefaultValue="" Comments="">
<OPTIONSELECTED>
<OPTIONSELECT Value="0" />
</OPTIONSELECTED>
</COLUMN>
<COLUMN ID="12800" ColName="IHEGR_TIPOEDAD" PrevColName="" Pos="13" idDatatype="19" DatatypeParams="(1)" Width="0" Prec="0" PrimaryKey="0" NotNull="1" AutoInc="0" IsForeignKey="0" DefaultValue="" Comments="">
<OPTIONSELECTED>
<OPTIONSELECT Value="0" />
</OPTIONSELECTED>
</COLUMN>
<COLUMN ID="12801" ColName="IHEGR_SEXO" PrevColName="" Pos="14" idDatatype="19" DatatypeParams="(1)" Width="0" Prec="0" PrimaryKey="0" NotNull="1" AutoInc="0" IsForeignKey="0" DefaultValue="" Comments="">
<OPTIONSELECTED>
<OPTIONSELECT Value="0" />
</OPTIONSELECTED>
</COLUMN>
<COLUMN ID="12802" ColName="IHEGR_TIPODOCUMMADRE" PrevColName="" Pos="15" idDatatype="19" DatatypeParams="(1)" Width="0" Prec="0" PrimaryKey="0" NotNull="1" AutoInc="0" IsForeignKey="0" DefaultValue="" Comments="">
<OPTIONSELECTED>
<OPTIONSELECT Value="0" />
</OPTIONSELECTED>
</COLUMN>
<COLUMN ID="12803" ColName="IHEGR_NRODOCUMMADRE" PrevColName="" Pos="16" idDatatype="20" DatatypeParams="(9)" Width="0" Prec="0" PrimaryKey="0" NotNull="1" AutoInc="0" IsForeignKey="0" DefaultValue="" Comments="">
<OPTIONSELECTED>
<OPTIONSELECT Value="0" />
</OPTIONSELECTED>
</COLUMN>
<COLUMN ID="12804" ColName="IHEGR_APELLIDO" PrevColName="" Pos="17" idDatatype="20" DatatypeParams="(30)" Width="0" Prec="0" PrimaryKey="0" NotNull="1" AutoInc="0" IsForeignKey="0" DefaultValue="" Comments="">
<OPTIONSELECTED>
<OPTIONSELECT Value="0" />
</OPTIONSELECTED>
</COLUMN>
<COLUMN ID="12805" ColName="IHEGR_NOMBRE" PrevColName="" Pos="18" idDatatype="20" DatatypeParams="(30)" Width="0" Prec="0" PrimaryKey="0" NotNull="1" AutoInc="0" IsForeignKey="0" DefaultValue="" Comments="">
<OPTIONSELECTED>
<OPTIONSELECT Value="0" />
</OPTIONSELECTED>
</COLUMN>
<COLUMN ID="12806" ColName="IHEGR_DIRECCION" PrevColName="" Pos="19" idDatatype="20" DatatypeParams="(30)" Width="0" Prec="0" PrimaryKey="0" NotNull="1" AutoInc="0" IsForeignKey="0" DefaultValue="" Comments="">
<OPTIONSELECTED>
<OPTIONSELECT Value="0" />
</OPTIONSELECTED>
</COLUMN>
<COLUMN ID="12807" ColName="IHEGR_DIRNRO" PrevColName="" Pos="20" idDatatype="20" DatatypeParams="(5)" Width="0" Prec="0" PrimaryKey="0" NotNull="1" AutoInc="0" IsForeignKey="0" DefaultValue="" Comments="">
<OPTIONSELECTED>
<OPTIONSELECT Value="0" />
</OPTIONSELECTED>
</COLUMN>
<COLUMN ID="12808" ColName="IHEGR_PISO" PrevColName="" Pos="21" idDatatype="20" DatatypeParams="(5)" Width="0" Prec="0" PrimaryKey="0" NotNull="1" AutoInc="0" IsForeignKey="0" DefaultValue="" Comments="">
<OPTIONSELECTED>
<OPTIONSELECT Value="0" />
</OPTIONSELECTED>
</COLUMN>
<COLUMN ID="12809" ColName="IHEGR_DEP" PrevColName="" Pos="22" idDatatype="20" DatatypeParams="(5)" Width="0" Prec="0" PrimaryKey="0" NotNull="1" AutoInc="0" IsForeignKey="0" DefaultValue="" Comments="">
<OPTIONSELECTED>
<OPTIONSELECT Value="0" />
</OPTIONSELECTED>
</COLUMN>
<COLUMN ID="12810" ColName="IHEGR_TELEFONO" PrevColName="" Pos="23" idDatatype="20" DatatypeParams="(15)" Width="0" Prec="0" PrimaryKey="0" NotNull="1" AutoInc="0" IsForeignKey="0" DefaultValue="" Comments="">
<OPTIONSELECTED>
<OPTIONSELECT Value="0" />
</OPTIONSELECTED>
</COLUMN>
<COLUMN ID="12811" ColName="IHEGR_BARRIO" PrevColName="" Pos="24" idDatatype="20" DatatypeParams="(25)" Width="0" Prec="0" PrimaryKey="0" NotNull="1" AutoInc="0" IsForeignKey="0" DefaultValue="" Comments="">
<OPTIONSELECTED>
<OPTIONSELECT Value="0" />
</OPTIONSELECTED>
</COLUMN>
<COLUMN ID="12812" ColName="IHEGR_LOCRESHAB" PrevColName="" Pos="25" idDatatype="19" DatatypeParams="(2)" Width="0" Prec="0" PrimaryKey="0" NotNull="1" AutoInc="0" IsForeignKey="0" DefaultValue="" Comments="">
<OPTIONSELECTED>
<OPTIONSELECT Value="0" />
</OPTIONSELECTED>
</COLUMN>
<COLUMN ID="12813" ColName="IHEGR_DPTORESHAB" PrevColName="" Pos="26" idDatatype="19" DatatypeParams="(3)" Width="0" Prec="0" PrimaryKey="0" NotNull="1" AutoInc="0" IsForeignKey="0" DefaultValue="" Comments="">
<OPTIONSELECTED>
<OPTIONSELECT Value="0" />
</OPTIONSELECTED>
</COLUMN>
<COLUMN ID="12814" ColName="IHEGR_PROVRESHAB" PrevColName="" Pos="27" idDatatype="19" DatatypeParams="(2)" Width="0" Prec="0" PrimaryKey="0" NotNull="1" AutoInc="0" IsForeignKey="0" DefaultValue="" Comments="">
<OPTIONSELECTED>
<OPTIONSELECT Value="0" />
</OPTIONSELECTED>
</COLUMN>
<COLUMN ID="12815" ColName="IHEGR_PAISRESHAB" PrevColName="" Pos="28" idDatatype="19" DatatypeParams="(3)" Width="0" Prec="0" PrimaryKey="0" NotNull="1" AutoInc="0" IsForeignKey="0" DefaultValue="" Comments="">
<OPTIONSELECTED>
<OPTIONSELECT Value="0" />
</OPTIONSELECTED>
</COLUMN>
<COLUMN ID="12816" ColName="IHEGR_OBRSOCIAL" PrevColName="" Pos="29" idDatatype="19" DatatypeParams="(1)" Width="0" Prec="0" PrimaryKey="0" NotNull="1" AutoInc="0" IsForeignKey="0" DefaultValue="" Comments="">
<OPTIONSELECTED>
<OPTIONSELECT Value="0" />
</OPTIONSELECTED>
</COLUMN>
<COLUMN ID="12817" ColName="IHEGR_CODOBRSOCIAL" PrevColName="" Pos="30" idDatatype="20" DatatypeParams="(5)" Width="0" Prec="0" PrimaryKey="0" NotNull="1" AutoInc="0" IsForeignKey="0" DefaultValue="" Comments="">
<OPTIONSELECTED>
<OPTIONSELECT Value="0" />
</OPTIONSELECTED>
</COLUMN>
<COLUMN ID="12818" ColName="IHEGR_CONDICION" PrevColName="" Pos="31" idDatatype="19" DatatypeParams="(1)" Width="0" Prec="0" PrimaryKey="0" NotNull="1" AutoInc="0" IsForeignKey="0" DefaultValue="" Comments="">
<OPTIONSELECTED>
<OPTIONSELECT Value="0" />
</OPTIONSELECTED>
</COLUMN>
<COLUMN ID="12819" ColName="IHEGR_INSTRUCCION" PrevColName="" Pos="32" idDatatype="19" DatatypeParams="(1)" Width="0" Prec="0" PrimaryKey="0" NotNull="1" AutoInc="0" IsForeignKey="0" DefaultValue="" Comments="">
<OPTIONSELECTED>
<OPTIONSELECT Value="0" />
</OPTIONSELECTED>
</COLUMN>
<COLUMN ID="12820" ColName="IHEGR_SISTEDUNOREF" PrevColName="" Pos="33" idDatatype="19" DatatypeParams="(1)" Width="0" Prec="0" PrimaryKey="0" NotNull="1" AutoInc="0" IsForeignKey="0" DefaultValue="" Comments="">
<OPTIONSELECTED>
<OPTIONSELECT Value="0" />
</OPTIONSELECTED>
</COLUMN>
<COLUMN ID="12821" ColName="IHEGR_SISTEDUREF" PrevColName="" Pos="34" idDatatype="19" DatatypeParams="(1)" Width="0" Prec="0" PrimaryKey="0" NotNull="1" AutoInc="0" IsForeignKey="0" DefaultValue="" Comments="">
<OPTIONSELECTED>
<OPTIONSELECT Value="0" />
</OPTIONSELECTED>
</COLUMN>
<COLUMN ID="12822" ColName="IHEGR_SUPUNIV" PrevColName="" Pos="35" idDatatype="19" DatatypeParams="(1)" Width="0" Prec="0" PrimaryKey="0" NotNull="1" AutoInc="0" IsForeignKey="0" DefaultValue="" Comments="">
<OPTIONSELECTED>
<OPTIONSELECT Value="0" />
</OPTIONSELECTED>
</COLUMN>
<COLUMN ID="12823" ColName="IHEGR_SITLABORAL" PrevColName="" Pos="36" idDatatype="19" DatatypeParams="(1)" Width="0" Prec="0" PrimaryKey="0" NotNull="1" AutoInc="0" IsForeignKey="0" DefaultValue="" Comments="">
<OPTIONSELECTED>
<OPTIONSELECT Value="0" />
</OPTIONSELECTED>
</COLUMN>
<COLUMN ID="12824" ColName="IHEGR_OCUPHABITUAL" PrevColName="" Pos="37" idDatatype="20" DatatypeParams="(5)" Width="0" Prec="0" PrimaryKey="0" NotNull="1" AutoInc="0" IsForeignKey="0" DefaultValue="" Comments="">
<OPTIONSELECTED>
<OPTIONSELECT Value="0" />
</OPTIONSELECTED>
</COLUMN>
<COLUMN ID="12825" ColName="IHEGR_HOSPPOR" PrevColName="" Pos="38" idDatatype="19" DatatypeParams="(1)" Width="0" Prec="0" PrimaryKey="0" NotNull="1" AutoInc="0" IsForeignKey="0" DefaultValue="" Comments="">
<OPTIONSELECTED>
<OPTIONSELECT Value="0" />
</OPTIONSELECTED>
</COLUMN>
<COLUMN ID="12826" ColName="IHEGR_HORAING" PrevColName="" Pos="39" idDatatype="20" DatatypeParams="(5)" Width="0" Prec="0" PrimaryKey="0" NotNull="1" AutoInc="0" IsForeignKey="0" DefaultValue="" Comments="">
<OPTIONSELECTED>
<OPTIONSELECT Value="0" />
</OPTIONSELECTED>
</COLUMN>
<COLUMN ID="12827" ColName="IHEGR_INGDERIVADOR" PrevColName="" Pos="40" idDatatype="19" DatatypeParams="(1)" Width="0" Prec="0" PrimaryKey="0" NotNull="1" AutoInc="0" IsForeignKey="0" DefaultValue="" Comments="">
<OPTIONSELECTED>
<OPTIONSELECT Value="0" />
</OPTIONSELECTED>
</COLUMN>
<COLUMN ID="12828" ColName="IHEGR_DIAING" PrevColName="" Pos="41" idDatatype="19" DatatypeParams="(2)" Width="0" Prec="0" PrimaryKey="0" NotNull="1" AutoInc="0" IsForeignKey="0" DefaultValue="" Comments="">
<OPTIONSELECTED>
<OPTIONSELECT Value="0" />
</OPTIONSELECTED>
</COLUMN>
<COLUMN ID="12829" ColName="IHEGR_MESING" PrevColName="" Pos="42" idDatatype="19" DatatypeParams="(2)" Width="0" Prec="0" PrimaryKey="0" NotNull="1" AutoInc="0" IsForeignKey="0" DefaultValue="" Comments="">
<OPTIONSELECTED>
<OPTIONSELECT Value="0" />
</OPTIONSELECTED>
</COLUMN>
<COLUMN ID="12830" ColName="IHEGR_ANOING" PrevColName="" Pos="43" idDatatype="20" DatatypeParams="(4)" Width="0" Prec="0" PrimaryKey="0" NotNull="1" AutoInc="0" IsForeignKey="0" DefaultValue="" Comments="">
<OPTIONSELECTED>
<OPTIONSELECT Value="0" />
</OPTIONSELECTED>
</COLUMN>
<COLUMN ID="12831" ColName="IHEGR_SERVING" PrevColName="" Pos="44" idDatatype="19" DatatypeParams="(3)" Width="0" Prec="0" PrimaryKey="0" NotNull="1" AutoInc="0" IsForeignKey="0" DefaultValue="" Comments="">
<OPTIONSELECTED>
<OPTIONSELECT Value="0" />
</OPTIONSELECTED>
</COLUMN>
<COLUMN ID="12832" ColName="IHEGR_SECINGRESO" PrevColName="" Pos="45" idDatatype="19" DatatypeParams="(1)" Width="0" Prec="0" PrimaryKey="0" NotNull="1" AutoInc="0" IsForeignKey="0" DefaultValue="" Comments="">
<OPTIONSELECTED>
<OPTIONSELECT Value="0" />
</OPTIONSELECTED>
</COLUMN>
<COLUMN ID="12833" ColName="IHEGR_SUBSECING" PrevColName="" Pos="46" idDatatype="19" DatatypeParams="(1)" Width="0" Prec="0" PrimaryKey="0" NotNull="1" AutoInc="0" IsForeignKey="0" DefaultValue="" Comments="">
<OPTIONSELECTED>
<OPTIONSELECT Value="0" />
</OPTIONSELECTED>
</COLUMN>
<COLUMN ID="12834" ColName="IHEGR_ESTADAING" PrevColName="" Pos="47" idDatatype="20" DatatypeParams="(5)" Width="0" Prec="0" PrimaryKey="0" NotNull="1" AutoInc="0" IsForeignKey="0" DefaultValue="" Comments="">
<OPTIONSELECTED>
<OPTIONSELECT Value="0" />
</OPTIONSELECTED>
</COLUMN>
<COLUMN ID="12835" ColName="IHEGR_EGRPOR" PrevColName="" Pos="48" idDatatype="19" DatatypeParams="(1)" Width="0" Prec="0" PrimaryKey="0" NotNull="1" AutoInc="0" IsForeignKey="0" DefaultValue="" Comments="">
<OPTIONSELECTED>
<OPTIONSELECT Value="0" />
</OPTIONSELECTED>
</COLUMN>
<COLUMN ID="12836" ColName="IHEGR_HORAEGR" PrevColName="" Pos="49" idDatatype="20" DatatypeParams="(5)" Width="0" Prec="0" PrimaryKey="0" NotNull="1" AutoInc="0" IsForeignKey="0" DefaultValue="" Comments="">
<OPTIONSELECTED>
<OPTIONSELECT Value="0" />
</OPTIONSELECTED>
</COLUMN>
<COLUMN ID="12837" ColName="IHEGR_DIAEGRESO" PrevColName="" Pos="50" idDatatype="19" DatatypeParams="(2)" Width="0" Prec="0" PrimaryKey="0" NotNull="1" AutoInc="0" IsForeignKey="0" DefaultValue="" Comments="">
<OPTIONSELECTED>
<OPTIONSELECT Value="0" />
</OPTIONSELECTED>
</COLUMN>
<COLUMN ID="12838" ColName="IHEGR_MESEGRESO" PrevColName="" Pos="51" idDatatype="19" DatatypeParams="(2)" Width="0" Prec="0" PrimaryKey="0" NotNull="1" AutoInc="0" IsForeignKey="0" DefaultValue="" Comments="">
<OPTIONSELECTED>
<OPTIONSELECT Value="0" />
</OPTIONSELECTED>
</COLUMN>
<COLUMN ID="12839" ColName="IHEGR_ANOEGRESO" PrevColName="" Pos="52" idDatatype="20" DatatypeParams="(4)" Width="0" Prec="0" PrimaryKey="0" NotNull="1" AutoInc="0" IsForeignKey="0" DefaultValue="" Comments="">
<OPTIONSELECTED>
<OPTIONSELECT Value="0" />
</OPTIONSELECTED>
</COLUMN>
<COLUMN ID="12840" ColName="IHEGR_ESTADATOTAL" PrevColName="" Pos="53" idDatatype="20" DatatypeParams="(5)" Width="0" Prec="0" PrimaryKey="0" NotNull="1" AutoInc="0" IsForeignKey="0" DefaultValue="" Comments="">
<OPTIONSELECTED>
<OPTIONSELECT Value="0" />
</OPTIONSELECTED>
</COLUMN>
<COLUMN ID="12841" ColName="IHEGR_CASOSOCIAL" PrevColName="" Pos="54" idDatatype="19" DatatypeParams="(1)" Width="0" Prec="0" PrimaryKey="0" NotNull="1" AutoInc="0" IsForeignKey="0" DefaultValue="" Comments="">
<OPTIONSELECTED>
<OPTIONSELECT Value="0" />
</OPTIONSELECTED>
</COLUMN>
<COLUMN ID="12842" ColName="IHEGR_DIASPOSTALTA" PrevColName="" Pos="55" idDatatype="20" DatatypeParams="(5)" Width="0" Prec="0" PrimaryKey="0" NotNull="1" AutoInc="0" IsForeignKey="0" DefaultValue="" Comments="">
<OPTIONSELECTED>
<OPTIONSELECT Value="0" />
</OPTIONSELECTED>
</COLUMN>
<COLUMN ID="12843" ColName="IHEGR_OTRASCIRCUNSTANCIAS" PrevColName="" Pos="56" idDatatype="20" DatatypeParams="(30)" Width="0" Prec="0" PrimaryKey="0" NotNull="1" AutoInc="0" IsForeignKey="0" DefaultValue="" Comments="">
<OPTIONSELECTED>
<OPTIONSELECT Value="0" />
</OPTIONSELECTED>
</COLUMN>
<COLUMN ID="12844" ColName="IHEGR_SERVEGR" PrevColName="" Pos="57" idDatatype="19" DatatypeParams="(3)" Width="0" Prec="0" PrimaryKey="0" NotNull="1" AutoInc="0" IsForeignKey="0" DefaultValue="" Comments="">
<OPTIONSELECTED>
<OPTIONSELECT Value="0" />
</OPTIONSELECTED>
</COLUMN>
<COLUMN ID="12845" ColName="IHEGR_SECEGR" PrevColName="" Pos="58" idDatatype="19" DatatypeParams="(1)" Width="0" Prec="0" PrimaryKey="0" NotNull="1" AutoInc="0" IsForeignKey="0" DefaultValue="" Comments="">
<OPTIONSELECTED>
<OPTIONSELECT Value="0" />
</OPTIONSELECTED>
</COLUMN>
<COLUMN ID="12846" ColName="IHEGR_SUBSECEGR" PrevColName="" Pos="59" idDatatype="19" DatatypeParams="(1)" Width="0" Prec="0" PrimaryKey="0" NotNull="1" AutoInc="0" IsForeignKey="0" DefaultValue="" Comments="">
<OPTIONSELECTED>
<OPTIONSELECT Value="0" />
</OPTIONSELECTED>
</COLUMN>
<COLUMN ID="12847" ColName="IHEGR_ESPPREDOMINANTE" PrevColName="" Pos="60" idDatatype="19" DatatypeParams="(3)" Width="0" Prec="0" PrimaryKey="0" NotNull="1" AutoInc="0" IsForeignKey="0" DefaultValue="" Comments="">
<OPTIONSELECTED>
<OPTIONSELECT Value="0" />
</OPTIONSELECTED>
</COLUMN>
<COLUMN ID="12848" ColName="IHEGR_DIAGPRINCIPAL" PrevColName="" Pos="61" idDatatype="20" DatatypeParams="(5)" Width="0" Prec="0" PrimaryKey="0" NotNull="1" AutoInc="0" IsForeignKey="0" DefaultValue="" Comments="">
<OPTIONSELECTED>
<OPTIONSELECT Value="0" />
</OPTIONSELECTED>
</COLUMN>
<COLUMN ID="12849" ColName="IHEGR_DESCDIAGP" PrevColName="" Pos="62" idDatatype="20" DatatypeParams="(80)" Width="0" Prec="0" PrimaryKey="0" NotNull="1" AutoInc="0" IsForeignKey="0" DefaultValue="" Comments="">
<OPTIONSELECTED>
<OPTIONSELECT Value="0" />
</OPTIONSELECTED>
</COLUMN>
<COLUMN ID="12850" ColName="IHEGR_OTRODIAG" PrevColName="" Pos="63" idDatatype="20" DatatypeParams="(5)" Width="0" Prec="0" PrimaryKey="0" NotNull="1" AutoInc="0" IsForeignKey="0" DefaultValue="" Comments="">
<OPTIONSELECTED>
<OPTIONSELECT Value="0" />
</OPTIONSELECTED>
</COLUMN>
<COLUMN ID="12851" ColName="IHEGR_OTRODIAG2" PrevColName="" Pos="64" idDatatype="20" DatatypeParams="(5)" Width="0" Prec="0" PrimaryKey="0" NotNull="1" AutoInc="0" IsForeignKey="0" DefaultValue="" Comments="">
<OPTIONSELECTED>
<OPTIONSELECT Value="0" />
</OPTIONSELECTED>
</COLUMN>
<COLUMN ID="12852" ColName="IHEGR_OTRODIAG3" PrevColName="" Pos="65" idDatatype="20" DatatypeParams="(5)" Width="0" Prec="0" PrimaryKey="0" NotNull="1" AutoInc="0" IsForeignKey="0" DefaultValue="" Comments="">
<OPTIONSELECTED>
<OPTIONSELECT Value="0" />
</OPTIONSELECTED>
</COLUMN>
<COLUMN ID="12853" ColName="IHEGR_OTRODIAG4" PrevColName="" Pos="66" idDatatype="20" DatatypeParams="(5)" Width="0" Prec="0" PrimaryKey="0" NotNull="1" AutoInc="0" IsForeignKey="0" DefaultValue="" Comments="">
<OPTIONSELECTED>
<OPTIONSELECT Value="0" />
</OPTIONSELECTED>
</COLUMN>
<COLUMN ID="12854" ColName="IHEGR_PROQUIOBS" PrevColName="" Pos="67" idDatatype="19" DatatypeParams="(1)" Width="0" Prec="0" PrimaryKey="0" NotNull="1" AutoInc="0" IsForeignKey="0" DefaultValue="" Comments="">
<OPTIONSELECTED>
<OPTIONSELECT Value="0" />
</OPTIONSELECTED>
</COLUMN>
<COLUMN ID="12855" ColName="IHEGR_OPERADO" PrevColName="" Pos="68" idDatatype="19" DatatypeParams="(1)" Width="0" Prec="0" PrimaryKey="0" NotNull="1" AutoInc="0" IsForeignKey="0" DefaultValue="" Comments="">
<OPTIONSELECTED>
<OPTIONSELECT Value="0" />
</OPTIONSELECTED>
</COLUMN>
<COLUMN ID="12856" ColName="IHEGR_DDFECOPER" PrevColName="" Pos="69" idDatatype="19" DatatypeParams="(2)" Width="0" Prec="0" PrimaryKey="0" NotNull="1" AutoInc="0" IsForeignKey="0" DefaultValue="" Comments="">
<OPTIONSELECTED>
<OPTIONSELECT Value="0" />
</OPTIONSELECTED>
</COLUMN>
<COLUMN ID="12857" ColName="IHEGR_MMFECOPER" PrevColName="" Pos="70" idDatatype="19" DatatypeParams="(2)" Width="0" Prec="0" PrimaryKey="0" NotNull="1" AutoInc="0" IsForeignKey="0" DefaultValue="" Comments="">
<OPTIONSELECTED>
<OPTIONSELECT Value="0" />
</OPTIONSELECTED>
</COLUMN>
<COLUMN ID="12858" ColName="IHEGR_AAFECOPER" PrevColName="" Pos="71" idDatatype="20" DatatypeParams="(4)" Width="0" Prec="0" PrimaryKey="0" NotNull="1" AutoInc="0" IsForeignKey="0" DefaultValue="" Comments="">
<OPTIONSELECTED>
<OPTIONSELECT Value="0" />
</OPTIONSELECTED>
</COLUMN>
<COLUMN ID="12859" ColName="IHEGR_TIEMPOPREO" PrevColName="" Pos="72" idDatatype="19" DatatypeParams="(3)" Width="0" Prec="0" PrimaryKey="0" NotNull="1" AutoInc="0" IsForeignKey="0" DefaultValue="" Comments="">
<OPTIONSELECTED>
<OPTIONSELECT Value="0" />
</OPTIONSELECTED>
</COLUMN>
<COLUMN ID="12860" ColName="IHEGR_OPERPRINCIPAL" PrevColName="" Pos="73" idDatatype="20" DatatypeParams="(4)" Width="0" Prec="0" PrimaryKey="0" NotNull="1" AutoInc="0" IsForeignKey="0" DefaultValue="" Comments="">
<OPTIONSELECTED>
<OPTIONSELECT Value="0" />
</OPTIONSELECTED>
</COLUMN>
<COLUMN ID="12861" ColName="IHEGR_OTRAOPER" PrevColName="" Pos="74" idDatatype="20" DatatypeParams="(4)" Width="0" Prec="0" PrimaryKey="0" NotNull="1" AutoInc="0" IsForeignKey="0" DefaultValue="" Comments="">
<OPTIONSELECTED>
<OPTIONSELECT Value="0" />
</OPTIONSELECTED>
</COLUMN>
<COLUMN ID="12862" ColName="IHEGR_OTRAOPER2" PrevColName="" Pos="75" idDatatype="20" DatatypeParams="(4)" Width="0" Prec="0" PrimaryKey="0" NotNull="1" AutoInc="0" IsForeignKey="0" DefaultValue="" Comments="">
<OPTIONSELECTED>
<OPTIONSELECT Value="0" />
</OPTIONSELECTED>
</COLUMN>
<COLUMN ID="12863" ColName="IHEGR_AUTOPSIA" PrevColName="" Pos="76" idDatatype="19" DatatypeParams="(1)" Width="0" Prec="0" PrimaryKey="0" NotNull="1" AutoInc="0" IsForeignKey="0" DefaultValue="" Comments="">
<OPTIONSELECTED>
<OPTIONSELECT Value="0" />
</OPTIONSELECTED>
</COLUMN>
<COLUMN ID="12864" ColName="IHEGR_LESION" PrevColName="" Pos="77" idDatatype="19" DatatypeParams="(1)" Width="0" Prec="0" PrimaryKey="0" NotNull="1" AutoInc="0" IsForeignKey="0" DefaultValue="" Comments="">
<OPTIONSELECTED>
<OPTIONSELECT Value="0" />
</OPTIONSELECTED>
</COLUMN>
<COLUMN ID="12865" ColName="IHEGR_LUGOCURRENCIA" PrevColName="" Pos="78" idDatatype="19" DatatypeParams="(1)" Width="0" Prec="0" PrimaryKey="0" NotNull="1" AutoInc="0" IsForeignKey="0" DefaultValue="" Comments="">
<OPTIONSELECTED>
<OPTIONSELECT Value="0" />
</OPTIONSELECTED>
</COLUMN>
<COLUMN ID="12866" ColName="IHEGR_CAUSAEXTERNA" PrevColName="" Pos="79" idDatatype="20" DatatypeParams="(5)" Width="0" Prec="0" PrimaryKey="0" NotNull="1" AutoInc="0" IsForeignKey="0" DefaultValue="" Comments="">
<OPTIONSELECTED>
<OPTIONSELECT Value="0" />
</OPTIONSELECTED>
</COLUMN>
<COLUMN ID="12867" ColName="IHEGR_TIPOPARTO" PrevColName="" Pos="80" idDatatype="19" DatatypeParams="(1)" Width="0" Prec="0" PrimaryKey="0" NotNull="1" AutoInc="0" IsForeignKey="0" DefaultValue="" Comments="">
<OPTIONSELECTED>
<OPTIONSELECT Value="0" />
</OPTIONSELECTED>
</COLUMN>
<COLUMN ID="12868" ColName="IHEGR_CONDALNACER" PrevColName="" Pos="81" idDatatype="19" DatatypeParams="(1)" Width="0" Prec="0" PrimaryKey="0" NotNull="1" AutoInc="0" IsForeignKey="0" DefaultValue="" Comments="">
<OPTIONSELECTED>
<OPTIONSELECT Value="0" />
</OPTIONSELECTED>
</COLUMN>
<COLUMN ID="12869" ColName="IHEGR_SEXONACIDO" PrevColName="" Pos="82" idDatatype="19" DatatypeParams="(1)" Width="0" Prec="0" PrimaryKey="0" NotNull="1" AutoInc="0" IsForeignKey="0" DefaultValue="" Comments="">
<OPTIONSELECTED>
<OPTIONSELECT Value="0" />
</OPTIONSELECTED>
</COLUMN>
<COLUMN ID="12870" ColName="IHEGR_PESO" PrevColName="" Pos="83" idDatatype="20" DatatypeParams="(4)" Width="0" Prec="0" PrimaryKey="0" NotNull="1" AutoInc="0" IsForeignKey="0" DefaultValue="" Comments="">
<OPTIONSELECTED>
<OPTIONSELECT Value="0" />
</OPTIONSELECTED>
</COLUMN>
<COLUMN ID="12871" ColName="IHEGR_TERMINACION" PrevColName="" Pos="84" idDatatype="19" DatatypeParams="(1)" Width="0" Prec="0" PrimaryKey="0" NotNull="1" AutoInc="0" IsForeignKey="0" DefaultValue="" Comments="">
<OPTIONSELECTED>
<OPTIONSELECT Value="0" />
</OPTIONSELECTED>
</COLUMN>
<COLUMN ID="12872" ColName="IHEGR_EDADGESTACION" PrevColName="" Pos="85" idDatatype="19" DatatypeParams="(2)" Width="0" Prec="0" PrimaryKey="0" NotNull="1" AutoInc="0" IsForeignKey="0" DefaultValue="" Comments="">
<OPTIONSELECTED>
<OPTIONSELECT Value="0" />
</OPTIONSELECTED>
</COLUMN>
<COLUMN ID="12873" ColName="IHEGR_PARIDAD" PrevColName="" Pos="86" idDatatype="19" DatatypeParams="(2)" Width="0" Prec="0" PrimaryKey="0" NotNull="1" AutoInc="0" IsForeignKey="0" DefaultValue="" Comments="">
<OPTIONSELECTED>
<OPTIONSELECT Value="0" />
</OPTIONSELECTED>
</COLUMN>
<COLUMN ID="12874" ColName="IHEGR_DIATERMEMB" PrevColName="" Pos="87" idDatatype="19" DatatypeParams="(2)" Width="0" Prec="0" PrimaryKey="0" NotNull="1" AutoInc="0" IsForeignKey="0" DefaultValue="" Comments="">
<OPTIONSELECTED>
<OPTIONSELECT Value="0" />
</OPTIONSELECTED>
</COLUMN>
<COLUMN ID="12875" ColName="IHEGR_MESTERMEMB" PrevColName="" Pos="88" idDatatype="19" DatatypeParams="(2)" Width="0" Prec="0" PrimaryKey="0" NotNull="1" AutoInc="0" IsForeignKey="0" DefaultValue="" Comments="">
<OPTIONSELECTED>
<OPTIONSELECT Value="0" />
</OPTIONSELECTED>
</COLUMN>
<COLUMN ID="12876" ColName="IHEGR_ANOTERMEMB" PrevColName="" Pos="89" idDatatype="20" DatatypeParams="(4)" Width="0" Prec="0" PrimaryKey="0" NotNull="1" AutoInc="0" IsForeignKey="0" DefaultValue="" Comments="">
<OPTIONSELECTED>
<OPTIONSELECT Value="0" />
</OPTIONSELECTED>
</COLUMN>
<COLUMN ID="12877" ColName="IHEGR_USUARIO" PrevColName="" Pos="90" idDatatype="20" DatatypeParams="(10)" Width="0" Prec="0" PrimaryKey="0" NotNull="1" AutoInc="0" IsForeignKey="0" DefaultValue="" Comments="">
<OPTIONSELECTED>
<OPTIONSELECT Value="0" />
</OPTIONSELECTED>
</COLUMN>
<COLUMN ID="12878" ColName="IHEGR_FECHAREGISTRACION" PrevColName="" Pos="91" idDatatype="14" DatatypeParams="" Width="0" Prec="0" PrimaryKey="0" NotNull="1" AutoInc="0" IsForeignKey="0" DefaultValue="0000-00-00" Comments="">
<OPTIONSELECTED>
</OPTIONSELECTED>
</COLUMN>
<COLUMN ID="12879" ColName="IHEGR_FECHAEGRESO" PrevColName="" Pos="92" idDatatype="14" DatatypeParams="" Width="0" Prec="0" PrimaryKey="0" NotNull="1" AutoInc="0" IsForeignKey="0" DefaultValue="0000-00-00" Comments="">
<OPTIONSELECTED>
</OPTIONSELECTED>
</COLUMN>
</COLUMNS>
<INDICES>
<INDEX ID="12880" IndexName="PRIMARY" IndexKind="0" FKRefDef_Obj_id="-1">
<INDEXCOLUMNS>
<INDEXCOLUMN idColumn="12788" LengthParam="0" />
<INDEXCOLUMN idColumn="12789" LengthParam="0" />
<INDEXCOLUMN idColumn="12790" LengthParam="0" />
<INDEXCOLUMN idColumn="12791" LengthParam="0" />
<INDEXCOLUMN idColumn="12792" LengthParam="0" />
<INDEXCOLUMN idColumn="12793" LengthParam="0" />
<INDEXCOLUMN idColumn="12794" LengthParam="0" />
</INDEXCOLUMNS>
</INDEX>
<INDEX ID="12881" IndexName="IHEGR_DIAGPRINCIPAL" IndexKind="1" FKRefDef_Obj_id="-1">
<INDEXCOLUMNS>
<INDEXCOLUMN idColumn="12848" LengthParam="0" />
<INDEXCOLUMN idColumn="12801" LengthParam="0" />
</INDEXCOLUMNS>
</INDEX>
<INDEX ID="12882" IndexName="IHEGR_FECHAEGRESO" IndexKind="1" FKRefDef_Obj_id="-1">
<INDEXCOLUMNS>
<INDEXCOLUMN idColumn="12879" LengthParam="0" />
</INDEXCOLUMNS>
</INDEX>
<INDEX ID="12883" IndexName="IHEGR_ANOINFORME" IndexKind="1" FKRefDef_Obj_id="-1">
<INDEXCOLUMNS>
<INDEXCOLUMN idColumn="12793" LengthParam="0" />
</INDEXCOLUMNS>
</INDEX>
<INDEX ID="12884" IndexName="IHEGR_CODDPTO" IndexKind="1" FKRefDef_Obj_id="-1">
<INDEXCOLUMNS>
<INDEXCOLUMN idColumn="12789" LengthParam="0" />
</INDEXCOLUMNS>
</INDEX>
<INDEX ID="12885" IndexName="IHEGR_CODEST" IndexKind="1" FKRefDef_Obj_id="-1">
<INDEXCOLUMNS>
<INDEXCOLUMN idColumn="12791" LengthParam="0" />
</INDEXCOLUMNS>
</INDEX>
<INDEX ID="12886" IndexName="IHEGR_PAISRESHAB" IndexKind="1" FKRefDef_Obj_id="-1">
<INDEXCOLUMNS>
<INDEXCOLUMN idColumn="12813" LengthParam="0" />
<INDEXCOLUMN idColumn="12814" LengthParam="0" />
<INDEXCOLUMN idColumn="12815" LengthParam="0" />
</INDEXCOLUMNS>
</INDEX>
<INDEX ID="12887" IndexName="IHEGR_nroInforme" IndexKind="1" FKRefDef_Obj_id="-1">
<INDEXCOLUMNS>
<INDEXCOLUMN idColumn="12789" LengthParam="0" />
<INDEXCOLUMN idColumn="12790" LengthParam="0" />
<INDEXCOLUMN idColumn="12791" LengthParam="0" />
<INDEXCOLUMN idColumn="12793" LengthParam="0" />
<INDEXCOLUMN idColumn="12794" LengthParam="0" />
</INDEXCOLUMNS>
</INDEX>
<INDEX ID="12888" IndexName="IHEGR_USUARIO" IndexKind="1" FKRefDef_Obj_id="-1">
<INDEXCOLUMNS>
<INDEXCOLUMN idColumn="12877" LengthParam="0" />
<INDEXCOLUMN idColumn="12788" LengthParam="0" />
<INDEXCOLUMN idColumn="12789" LengthParam="0" />
<INDEXCOLUMN idColumn="12790" LengthParam="0" />
<INDEXCOLUMN idColumn="12791" LengthParam="0" />
<INDEXCOLUMN idColumn="12838" LengthParam="0" />
<INDEXCOLUMN idColumn="12839" LengthParam="0" />
</INDEXCOLUMNS>
</INDEX>
</INDICES>
</TABLE>
</TABLES>
<RELATIONS>
</RELATIONS>
<NOTES>
</NOTES>
<IMAGES>
</IMAGES>
</METADATA>
<PLUGINDATA>
<PLUGINDATARECORDS>
</PLUGINDATARECORDS>
</PLUGINDATA>
<QUERYDATA>
<QUERYRECORDS>
</QUERYRECORDS>
</QUERYDATA>
<LINKEDMODELS>
</LINKEDMODELS>
</DBMODEL>
